{"YearStart": {"value_count 2021": 36648, "value_count 2017": 33428, "value_count 2019": 34353, "value_count 2020": 35309, "value_count 2015": 35019, "value_count 2016": 45626, "value_count 2018": 30547}, "LocationDesc": {"value_count West": 5369, "value_count Northeast": 5345, "value_count Midwest": 5342, "value_count United States, DC & Territories": 5375, "value_count New Hampshire": 3775, "value_count Illinois": 4164, "value_count Vermont": 4003, "value_count Connecticut": 4148, "value_count Utah": 4713, "value_count Nevada": 4307, "value_count California": 4083, "value_count Indiana": 4175, "value_count South": 5273, "value_count Puerto Rico": 3238, "value_count Idaho": 4149, "value_count Washington": 3863, "value_count Ohio": 4665, "value_count Wyoming": 4102, "value_count Guam": 3130, "value_count Florida": 3740, "value_count Maine": 4372, "value_count Delaware": 4089, "value_count Michigan": 4492, "value_count Colorado": 3965, "value_count Missouri": 4178, "value_count Kansas": 4115, "value_count Maryland": 4615, "value_count Wisconsin": 4312, "value_count Iowa": 4107, "value_count Texas": 4430, "value_count Virginia": 4273, "value_count Mississippi": 4380, "value_count Kentucky": 4254, "value_count Louisiana": 4157, "value_count Alaska": 4222, "value_count New Jersey": 4199, "value_count Arizona": 4073, "value_count Rhode Island": 4145, "value_count Alabama": 4270, "value_count Minnesota": 4160, "value_count South Carolina": 4230, "value_count Montana": 3839, "value_count North Dakota": 4141, "value_count New York": 5270, "value_count Massachusetts": 3895, "value_count Nebraska": 4154, "value_count New Mexico": 4264, "value_count Oregon": 5298, "value_count Hawaii": 4625, "value_count Georgia": 4538, "value_count Arkansas": 4101, "value_count West Virginia": 4317, "value_count District of Columbia": 4248, "value_count Tennessee": 4445, "value_count Pennsylvania": 4235, "value_count Virgin Islands": 1023, "value_count Oklahoma": 4226, "value_count South Dakota": 4173, "value_count North Carolina": 4089}, "Stratification1": {"value_count Overall": 84146, "value_count 65 years or older": 83094, "value_count 50-64 years": 83694}, "Stratification2": {"value_count Hispanic": 32204, "value_count nan": 32375, "value_count Female": 30275, "value_count Native Am/Alaskan Native": 31049, "value_count Male": 30275, "value_count Asian/Pacific Islander": 30772, "value_count Black, non-Hispanic": 31648, "value_count White, non-Hispanic": 32331}, "Data_Value_Alt": {"max_value": 100.0, "min_value": 0.0, "avg_value": 37.32834874957177, "sum_value": 6319764.1, "std_value": 25.21318058410274}, "Low_Confidence_Limit": {"max_value": 99.6, "min_value": -0.7, "avg_value": 32.69818833295885, "sum_value": 5530113.799999999, "std_value": 24.288903798755303}, "High_Confidence_Limit": {"max_value": 100.0, "min_value": 1.4, "avg_value": 42.24384009555006, "sum_value": 7144531.7, "std_value": 26.165896440063268}}